odoo/addons/stock_pack_operation_auto_fill/README.rst
odoo/addons/stock_pack_operation_auto_fill/__init__.py
odoo/addons/stock_pack_operation_auto_fill/__manifest__.py
odoo/addons/stock_pack_operation_auto_fill/i18n/cs_CZ.po
odoo/addons/stock_pack_operation_auto_fill/i18n/de.po
odoo/addons/stock_pack_operation_auto_fill/i18n/es.po
odoo/addons/stock_pack_operation_auto_fill/i18n/fr.po
odoo/addons/stock_pack_operation_auto_fill/i18n/it.po
odoo/addons/stock_pack_operation_auto_fill/i18n/nl_NL.po
odoo/addons/stock_pack_operation_auto_fill/i18n/pt.po
odoo/addons/stock_pack_operation_auto_fill/i18n/pt_BR.po
odoo/addons/stock_pack_operation_auto_fill/i18n/stock_pack_operation_auto_fill.pot
odoo/addons/stock_pack_operation_auto_fill/migrations/11.0.2.0.0/post-migrate.py
odoo/addons/stock_pack_operation_auto_fill/models/__init__.py
odoo/addons/stock_pack_operation_auto_fill/models/stock_move.py
odoo/addons/stock_pack_operation_auto_fill/models/stock_picking.py
odoo/addons/stock_pack_operation_auto_fill/models/stock_picking_type.py
odoo/addons/stock_pack_operation_auto_fill/readme/CONFIGURE.rst
odoo/addons/stock_pack_operation_auto_fill/readme/CONTRIBUTORS.rst
odoo/addons/stock_pack_operation_auto_fill/readme/DESCRIPTION.rst
odoo/addons/stock_pack_operation_auto_fill/readme/USAGE.rst
odoo/addons/stock_pack_operation_auto_fill/static/description/icon.png
odoo/addons/stock_pack_operation_auto_fill/static/description/index.html
odoo/addons/stock_pack_operation_auto_fill/tests/__init__.py
odoo/addons/stock_pack_operation_auto_fill/tests/test_stock_picking_auto_fill.py
odoo/addons/stock_pack_operation_auto_fill/views/stock_picking.xml
odoo/addons/stock_pack_operation_auto_fill/views/stock_picking_type_views.xml
odoo11_addon_stock_pack_operation_auto_fill-11.0.2.0.2.dist-info/METADATA
odoo11_addon_stock_pack_operation_auto_fill-11.0.2.0.2.dist-info/WHEEL
odoo11_addon_stock_pack_operation_auto_fill-11.0.2.0.2.dist-info/top_level.txt
odoo11_addon_stock_pack_operation_auto_fill-11.0.2.0.2.dist-info/RECORD
