Metadata-Version: 2.1
Name: odoo11-addon-stock-pack-operation-auto-fill
Version: 11.0.2.0.2
Summary: Stock pack operation auto fill
Home-page: https://github.com/stock-logistics-workflow/
Author: ACSONE SA/NV,Tecnativa,Odoo Community Association (OCA)
Author-email: support@odoo-community.org
License: AGPL-3
Platform: UNKNOWN
Classifier: Programming Language :: Python
Classifier: Framework :: Odoo
Classifier: License :: OSI Approved :: GNU Affero General Public License v3
Requires-Python: >=2.7, !=3.0.*, !=3.1.*, !=3.2.*, !=3.3.*, !=3.4.*
Requires-Dist: odoo (<11.1dev,>=11.0a)
